Workbook

Sheet DADOS_PRODUTOS
A1: RESTAURANTE SABOR DA VILA — Análise de Produtos | Outubro/2024
A2: Produto | B2: Categoria | C2: Canal | D2: Qtd_Vendida | E2: Preco_Venda | F2: Custo_Unitario | G2: Faturamento | H2: Custo_Total | I2: Lucro_Bruto | J2: Margem_Pct | K2: Lucro_Unitario | L2: Classificacao
A3: Marmita P | B3: Delivery | C3: iFood | D3: 400 | E3: 18.9 | F3: 7.2 | G3: =D3*E3 -> 7560 | H3: =D3*F3 -> 2880 | I3: =G3-H3 -> 4680 | J3: =I3/G3 -> 0.61904762 | K3: =E3-F3 -> 11.7 | L3: ESTRELA
A4: Marmita G | B4: Delivery | C4: iFood | D4: 260 | E4: 24.9 | F4: 9.8 | G4: =D4*E4 -> 6474 | H4: =D4*F4 -> 2548 | I4: =G4-H4 -> 3926 | J4: =I4/G4 -> 0.6064257 | K4: =E4-F4 -> 15.1 | L4: ESTRELA
A5: Prato Feito Frango | B5: Pratos | C5: Salão | D5: 330 | E5: 25.9 | F5: 10.8 | G5: =D5*E5 -> 8547 | H5: =D5*F5 -> 3564 | I5: =G5-H5 -> 4983 | J5: =I5/G5 -> 0.58301158 | K5: =E5-F5 -> 15.1 | L5: ESTRELA
A6: Prato Feito Carne | B6: Pratos | C6: Salão | D6: 240 | E6: 28.9 | F6: 13.5 | G6: =D6*E6 -> 6936 | H6: =D6*F6 -> 3240 | I6: =G6-H6 -> 3696 | J6: =I6/G6 -> 0.53287197 | K6: =E6-F6 -> 15.4 | L6: REVISAR
A7: Combo Executivo | B7: Pratos | C7: Salão | D7: 200 | E7: 34.9 | F7: 15 | G7: =D7*E7 -> 6980 | H7: =D7*F7 -> 3000 | I7: =G7-H7 -> 3980 | J7: =I7/G7 -> 0.57020057 | K7: =E7-F7 -> 19.9 | L7: POTENCIAL
A8: Refrigerante Lata | B8: Bebidas | C8: Ambos | D8: 490 | E8: 6 | F8: 1.8 | G8: =D8*E8 -> 2940 | H8: =D8*F8 -> 882 | I8: =G8-H8 -> 2058 | J8: =I8/G8 -> 0.7 | K8: =E8-F8 -> 4.2 | L8: ESTRELA
A9: Suco Natural | B9: Bebidas | C9: Ambos | D9: 160 | E9: 10 | F9: 2.5 | G9: =D9*E9 -> 1600 | H9: =D9*F9 -> 400 | I9: =G9-H9 -> 1200 | J9: =I9/G9 -> 0.75 | K9: =E9-F9 -> 7.5 | L9: OPORTUNIDADE
A10: Sobremesa | B10: Extras | C10: Ambos | D10: 110 | E10: 12 | F10: 3.2 | G10: =D10*E10 -> 1320 | H10: =D10*F10 -> 352 | I10: =G10-H10 -> 968 | J10: =I10/G10 -> 0.73333333 | K10: =E10-F10 -> 8.8 | L10: OPORTUNIDADE
A11: TOTAL | D11: =SUM(D3:D10) -> 2190 | G11: =SUM(G3:G10) -> 42357 | H11: =SUM(H3:H10) -> 16866 | I11: =SUM(I3:I10) -> 25491 | J11: =I11/G11 -> 0.60181316

Sheet HISTORICO_MENSAL
A1: RESTAURANTE SABOR DA VILA — Histórico Mensal | Jan–Out 2024
A2: Mes | B2: Ordem_Mes | C2: Faturamento | D2: Custo_Total | E2: Lucro_Bruto | F2: Margem_Pct | G2: CMV_Pct | H2: Ticket_Medio | I2: Qtd_Pedidos | J2: Cresc_Fat_Pct
A3: jan/24 | B3: 1 | C3: 32400 | D3: 14500 | E3: =C3-D3 -> 17900 | F3: =E3/C3 -> 0.55246914 | G3: =D3/C3 -> 0.44753086 | H3: 27.2 | I3: =ROUND(C3/H3,0) -> 1191 | J3: —
A4: fev/24 | B4: 2 | C4: 30100 | D4: 13500 | E4: =C4-D4 -> 16600 | F4: =E4/C4 -> 0.55149502 | G4: =D4/C4 -> 0.44850498 | H4: 26.8 | I4: =ROUND(C4/H4,0) -> 1123 | J4: =(C4-C3)/C3 -> -0.070987654
A5: mar/24 | B5: 3 | C5: 34800 | D5: 15600 | E5: =C5-D5 -> 19200 | F5: =E5/C5 -> 0.55172414 | G5: =D5/C5 -> 0.44827586 | H5: 28.1 | I5: =ROUND(C5/H5,0) -> 1238 | J5: =(C5-C4)/C4 -> 0.15614618
A6: abr/24 | B6: 4 | C6: 36200 | D6: 16200 | E6: =C6-D6 -> 20000 | F6: =E6/C6 -> 0.55248619 | G6: =D6/C6 -> 0.44751381 | H6: 28.8 | I6: =ROUND(C6/H6,0) -> 1257 | J6: =(C6-C5)/C5 -> 0.040229885
A7: mai/24 | B7: 5 | C7: 33600 | D7: 15000 | E7: =C7-D7 -> 18600 | F7: =E7/C7 -> 0.55357143 | G7: =D7/C7 -> 0.44642857 | H7: 27.5 | I7: =ROUND(C7/H7,0) -> 1222 | J7: =(C7-C6)/C6 -> -0.071823204
A8: jun/24 | B8: 6 | C8: 31800 | D8: 14200 | E8: =C8-D8 -> 17600 | F8: =E8/C8 -> 0.55345912 | G8: =D8/C8 -> 0.44654088 | H8: 27 | I8: =ROUND(C8/H8,0) -> 1178 | J8: =(C8-C7)/C7 -> -0.053571429
A9: jul/24 | B9: 7 | C9: 35900 | D9: 16100 | E9: =C9-D9 -> 19800 | F9: =E9/C9 -> 0.55153203 | G9: =D9/C9 -> 0.44846797 | H9: 29.2 | I9: =ROUND(C9/H9,0) -> 1229 | J9: =(C9-C8)/C8 -> 0.12893082
A10: ago/24 | B10: 8 | C10: 38400 | D10: 17200 | E10: =C10-D10 -> 21200 | F10: =E10/C10 -> 0.55208333 | G10: =D10/C10 -> 0.44791667 | H10: 30.1 | I10: =ROUND(C10/H10,0) -> 1276 | J10: =(C10-C9)/C9 -> 0.069637883
A11: set/24 | B11: 9 | C11: 40700 | D11: 18200 | E11: =C11-D11 -> 22500 | F11: =E11/C11 -> 0.55282555 | G11: =D11/C11 -> 0.44717445 | H11: 31 | I11: =ROUND(C11/H11,0) -> 1313 | J11: =(C11-C10)/C10 -> 0.059895833
A12: out/24 | B12: 10 | C12: 42357 | D12: 19000 | E12: =C12-D12 -> 23357 | F12: =E12/C12 -> 0.55143188 | G12: =D12/C12 -> 0.44856812 | H12: 31.8 | I12: =ROUND(C12/H12,0) -> 1332 | J12: =(C12-C11)/C11 -> 0.040712531

Sheet ANALISE_MARGEM
A1: ANÁLISE DE MARGEM — Posicionamento de Produtos | Out/2024
A2: Produto | B2: Categoria | C2: Faturamento | D2: Custo_Total | E2: Lucro_Bruto | F2: Margem_Pct | G2: Lucro_Unitario | H2: Classificacao
A3: =DADOS_PRODUTOS!A3 -> Marmita P | B3: =DADOS_PRODUTOS!B3 -> Delivery | C3: =DADOS_PRODUTOS!G3 -> 7560 | D3: =DADOS_PRODUTOS!H3 -> 2880 | E3: =DADOS_PRODUTOS!I3 -> 4680 | F3: =E3/C3 -> 0.61904762 | G3: =DADOS_PRODUTOS!K3 -> 11.7 | H3: =DADOS_PRODUTOS!L3 -> ESTRELA
A4: =DADOS_PRODUTOS!A4 -> Marmita G | B4: =DADOS_PRODUTOS!B4 -> Delivery | C4: =DADOS_PRODUTOS!G4 -> 6474 | D4: =DADOS_PRODUTOS!H4 -> 2548 | E4: =DADOS_PRODUTOS!I4 -> 3926 | F4: =E4/C4 -> 0.6064257 | G4: =DADOS_PRODUTOS!K4 -> 15.1 | H4: =DADOS_PRODUTOS!L4 -> ESTRELA
A5: =DADOS_PRODUTOS!A5 -> Prato Feito Frango | B5: =DADOS_PRODUTOS!B5 -> Pratos | C5: =DADOS_PRODUTOS!G5 -> 8547 | D5: =DADOS_PRODUTOS!H5 -> 3564 | E5: =DADOS_PRODUTOS!I5 -> 4983 | F5: =E5/C5 -> 0.58301158 | G5: =DADOS_PRODUTOS!K5 -> 15.1 | H5: =DADOS_PRODUTOS!L5 -> ESTRELA
A6: =DADOS_PRODUTOS!A6 -> Prato Feito Carne | B6: =DADOS_PRODUTOS!B6 -> Pratos | C6: =DADOS_PRODUTOS!G6 -> 6936 | D6: =DADOS_PRODUTOS!H6 -> 3240 | E6: =DADOS_PRODUTOS!I6 -> 3696 | F6: =E6/C6 -> 0.53287197 | G6: =DADOS_PRODUTOS!K6 -> 15.4 | H6: =DADOS_PRODUTOS!L6 -> REVISAR
A7: =DADOS_PRODUTOS!A7 -> Combo Executivo | B7: =DADOS_PRODUTOS!B7 -> Pratos | C7: =DADOS_PRODUTOS!G7 -> 6980 | D7: =DADOS_PRODUTOS!H7 -> 3000 | E7: =DADOS_PRODUTOS!I7 -> 3980 | F7: =E7/C7 -> 0.57020057 | G7: =DADOS_PRODUTOS!K7 -> 19.9 | H7: =DADOS_PRODUTOS!L7 -> POTENCIAL
A8: =DADOS_PRODUTOS!A8 -> Refrigerante Lata | B8: =DADOS_PRODUTOS!B8 -> Bebidas | C8: =DADOS_PRODUTOS!G8 -> 2940 | D8: =DADOS_PRODUTOS!H8 -> 882 | E8: =DADOS_PRODUTOS!I8 -> 2058 | F8: =E8/C8 -> 0.7 | G8: =DADOS_PRODUTOS!K8 -> 4.2 | H8: =DADOS_PRODUTOS!L8 -> ESTRELA
A9: =DADOS_PRODUTOS!A9 -> Suco Natural | B9: =DADOS_PRODUTOS!B9 -> Bebidas | C9: =DADOS_PRODUTOS!G9 -> 1600 | D9: =DADOS_PRODUTOS!H9 -> 400 | E9: =DADOS_PRODUTOS!I9 -> 1200 | F9: =E9/C9 -> 0.75 | G9: =DADOS_PRODUTOS!K9 -> 7.5 | H9: =DADOS_PRODUTOS!L9 -> OPORTUNIDADE
A10: =DADOS_PRODUTOS!A10 -> Sobremesa | B10: =DADOS_PRODUTOS!B10 -> Extras | C10: =DADOS_PRODUTOS!G10 -> 1320 | D10: =DADOS_PRODUTOS!H10 -> 352 | E10: =DADOS_PRODUTOS!I10 -> 968 | F10: =E10/C10 -> 0.73333333 | G10: =DADOS_PRODUTOS!K10 -> 8.8 | H10: =DADOS_PRODUTOS!L10 -> OPORTUNIDADE

Sheet INSIGHTS
A1: INSIGHTS ESTRATÉGICOS — Restaurante Sabor da Vila
A2: Insight | B2: Descrição e Ação Recomendada
A3: INSIGHT 1 — Suco Natural: margem mais alta, volume baixo | B3: Margem de 75,0% — a mais alta de todos os produtos — com apenas 160 unidades vendidas. Cada unidade gera R$7,50 de lucro. Potencial inexplorado de R$4.600/mês se volume dobrar. AÇÃO: treinar equipe para oferecer ativamente; adicionar como 'complemento sugerido' no iFood.
A4: INSIGHT 2 — Combo Executivo: ticket alto, margem sólida | B4: Ticket de R$34,90 (85% maior que Marmita P) com margem de 57,0%. Se 15% dos 400 pedidos de Marmita P migrassem para Combo, o faturamento adicional seria R$2.400/mês sem nenhum cliente novo. AÇÃO: criar promoção 'Combo do Dia' com destaque no iFood e cardápio físico.
A5: INSIGHT 3 — Refrigerante Lata: alto volume e margem surpreendente | B5: 490 unidades × margem 70,0% = R$2.058 de lucro apenas com bebidas. O item mais vendido em volume. AÇÃO: criar combo obrigatório 'prato + bebida' no salão; no iFood, adicionar como sugestão automática em todos os pratos.
A6: INSIGHT 4 — Prato Feito Carne: único abaixo de 55% de margem | B6: Margem de 53,3% — a mais baixa do cardápio. Custo de R$13,50 num prato de R$28,90. AÇÕES (escolha 1 ou combine): (a) renegociar fornecedor de carne buscando 10% de redução; (b) reduzir gramagem em 8%; (c) reajustar preço para R$31,90.
A7: INSIGHT 5 — Crescimento de 30,7% em 10 meses com margem estável | B7: Faturamento cresceu de R$32.400 (jan) para R$42.357 (out) — +30,7%. A margem oscilou entre 54% e 56% o tempo todo, indicando que custos crescem na mesma proporção. AÇÃO: negociar escala com fornecedores para reduzir CMV de 44% para 40%, o que geraria +R$1.690/mês de lucro adicional.
A8: INSIGHT 6 — iFood vs pedido direto: diferença real no lucro | B8: A comissão do iFood (média 23%) reduz a margem da Marmita P de 61,9% para 38,8% — uma diferença de R$2,63 por pedido. Com 400 pedidos/mês, são R$1.052 mensais pagos de comissão só na Marmita P. AÇÃO: criar canal de pedidos direto via WhatsApp com desconto de R$2,00 para o cliente — você ganha R$1,00 por pedido e fideliza.
